setup.cfg
setup.py
infoblox/__init__.py
infoblox/infoblox.py
infoblox/_internal/__init__.py
infoblox/_internal/a.py
infoblox/_internal/cname.py
infoblox/_internal/grid.py
infoblox/_internal/host.py
infoblox/_internal/lease.py
infoblox/_internal/mx.py
infoblox/_internal/rpz_cname.py
infoblox/_internal/srv.py
infoblox/_internal/subnet.py
infoblox/test/__init__.py
infoblox/test/sample.config.py
infoblox/test/test_infoblox.py
python_infoblox.egg-info/PKG-INFO
python_infoblox.egg-info/SOURCES.txt
python_infoblox.egg-info/dependency_links.txt
python_infoblox.egg-info/requires.txt
python_infoblox.egg-info/top_level.txt