Metadata-Version: 1.1
Name: python-infoblox
Version: 0.4
Summary: A wrapper around the Infoblox WAPI
Home-page: https://github.com/dylanfmarquis/python-infoblox
Author: Dylan F. Marquis
Author-email: dylanfmarquis@dylanfmarquis.com
License: MIT
Download-URL: https://github.com/dylanfmarquis/python-infoblox/archive/v0.4.0.tar.gz
Keywords: infoblox,wapi
Platform: UNKNOWN
